yesserpackageupdater/__init__.py
yesserpackageupdater/__main__.py
yesserpackageupdater-1.8.1.1.dist-info/LICENSE
yesserpackageupdater-1.8.1.1.dist-info/METADATA
yesserpackageupdater-1.8.1.1.dist-info/WHEEL
yesserpackageupdater-1.8.1.1.dist-info/entry_points.txt
yesserpackageupdater-1.8.1.1.dist-info/top_level.txt
yesserpackageupdater-1.8.1.1.dist-info/RECORD
