Metadata-Version: 2.1
Name: yesserpackageupdater
Version: 1.8.1.1
Summary: A simple pip package updater
Author-email: yesseruser <yesseruser@gmail.com>
Project-URL: Homepage, https://github.com/yesseruser/YesserPackageUpdater
Project-URL: Bug Tracker, https://github.com/yesseruser/YesserPackageUpdater/issues
Classifier: Programming Language :: Python :: 3
Classifier: License :: OSI Approved :: MIT License
Classifier: Operating System :: OS Independent
Requires-Python: >=3.7
License-File: LICENSE
